aioworkers_mqtt/__init__.py
aioworkers_mqtt/paho.py
aioworkers_mqtt/py.typed
aioworkers_mqtt-0.1.0.dist-info/METADATA
aioworkers_mqtt-0.1.0.dist-info/WHEEL
aioworkers_mqtt-0.1.0.dist-info/entry_points.txt
aioworkers_mqtt-0.1.0.dist-info/licenses/LICENSE
aioworkers_mqtt-0.1.0.dist-info/RECORD
