Metadata-Version: 2.4
Name: aioworkers-mqtt
Version: 0.1.0
Summary: aioworkers plugin integration to mqtt
Project-URL: Homepage, https://github.com/aioworkers/aioworkers-mqtt
Project-URL: Documentation, https://github.com/aioworkers/aioworkers-mqtt#readme
Project-URL: Issues, https://github.com/aioworkers/aioworkers-mqtt/issues
Project-URL: Source, https://github.com/aioworkers/aioworkers-mqtt
Author-email: Alexander Malev <malev@somedev.ru>
License-Expression: Apache-2.0
License-File: LICENSE
Keywords: aioworkers
Classifier: Development Status :: 4 - Beta
Classifier: Framework :: AsyncIO
Classifier: Intended Audience :: Developers
Classifier: License :: OSI Approved :: Apache Software License
Classifier: Programming Language :: Python :: 3
Classifier: Programming Language :: Python :: 3 :: Only
Classifier: Programming Language :: Python :: 3.9
Classifier: Programming Language :: Python :: 3.10
Classifier: Programming Language :: Python :: 3.11
Classifier: Programming Language :: Python :: 3.12
Classifier: Programming Language :: Python :: 3.13
Classifier: Programming Language :: Python :: Implementation :: CPython
Classifier: Programming Language :: Python :: Implementation :: PyPy
Requires-Python: >=3.9
Requires-Dist: aioworkers>=0.28.0
Provides-Extra: dev-lint
Requires-Dist: mypy==1.15.0; extra == 'dev-lint'
Requires-Dist: ruff==0.11.2; extra == 'dev-lint'
Provides-Extra: dev-test
Requires-Dist: aioworkers==0.28.0; extra == 'dev-test'
Requires-Dist: coverage[toml]==7.7.1; extra == 'dev-test'
Requires-Dist: pytest-aioworkers[asyncio]==0.5.0; extra == 'dev-test'
Requires-Dist: pytest-mock==3.14.0; extra == 'dev-test'
Requires-Dist: pytest-timeout>=2.3.1; extra == 'dev-test'
Requires-Dist: pytest==8.3.5; extra == 'dev-test'
Requires-Dist: pyyaml==6.0.2; extra == 'dev-test'
Provides-Extra: paho
Requires-Dist: paho-mqtt>=2.1.0; extra == 'paho'
